{"data":{"site":{"siteMetadata":{"title":"A Blog","author":"Scott Williams"}},"markdownRemark":{"id":"6bb08ca8-707a-5f68-ada5-d50016c0dd34","excerpt":"","html":"<div><div><div><div><div>The fact that&#xA0;<a href=\"http://www.teamfortress.com/post.php?id=4014&amp;p=\">Steam is releasing an official API</a>&#xA0;for their stuff is pretty cool, but the best part of their post is the photo that goes with it.<p></p>\n<div><img src=\"http://www.teamfortress.com/images/posts/stockphoto.jpg\"></div>\n</div></div></div></div></div>","frontmatter":{"title":"Stock Photo","date":"July 01, 2010"}}},"pageContext":{"slug":"/2010/07/01/stock-photo/index.html/","previous":{"fields":{"slug":"/2010/06/30/good-copy-woots-acquisition-post/index.html/"},"frontmatter":{"title":"Good Copy - Woot's Acquisition Post"}},"next":{"fields":{"slug":"/2010/07/01/meredith/index.html/"},"frontmatter":{"title":"Meredith"}}}}