{"data":{"site":{"siteMetadata":{"title":"A Blog","author":"Scott Williams"}},"markdownRemark":{"id":"23ab3a9d-f6af-5151-b6a9-59ea155cd531","excerpt":"From  Hacker News : Java is a bureaucratic language. You have to cross your t’s dot your i’s, fill out your requests in triplicate at the FactoryFactoryFactory…","html":"<p>From <a href=\"http://news.ycombinator.com/item?id=1463592\">Hacker News</a>:</p>\n<blockquote>\n<p>Java is a bureaucratic language. You have to cross your t’s dot your i’s, fill out your requests in triplicate at the FactoryFactoryFactory to get the objectOfYourDesire.</p>\n</blockquote>\n<p><span>(And probably C# too, but to a lesser extent :-p)</span></p>","frontmatter":{"title":"Java","date":"June 26, 2010"}}},"pageContext":{"slug":"/2010/06/26/java/","previous":{"fields":{"slug":"/2010/06/25/competitive-advantage-artists/"},"frontmatter":{"title":"Competitive Advantage: Artists"}},"next":{"fields":{"slug":"/2010/06/28/top-11-things-anyone-should-learn/"},"frontmatter":{"title":"Top 11 Things [Anyone] Should Learn"}}}}